countries_meta/__init__.py
countries_meta/countries.csv
countries_meta-0.1.0.dist-info/licenses/LICENSE
countries_meta-0.1.0.dist-info/METADATA
countries_meta-0.1.0.dist-info/WHEEL
countries_meta-0.1.0.dist-info/top_level.txt
countries_meta-0.1.0.dist-info/RECORD
