Metadata-Version: 2.4
Name: countries-meta
Version: 0.1.0
Summary: A Python module to access general countries information including name, origin name, dial code, currency, capital, timezone, and current time.
Author-email: EightShift <the8shift@gmail.com>
License-Expression: MIT
Project-URL: Homepage, https://github.com/EightShift/countries-meta
Keywords: python,countries,country-info,dial-code,currency,capital,timezone,geography,international
Requires-Python: >=3.9
License-File: LICENSE
Requires-Dist: tzdata>=2023.1
Dynamic: license-file
